ezneis/__init__.py
ezneis/exceptions.py
ezneis/data/__init__.py
ezneis/data/academy/__init__.py
ezneis/data/academy/asynchronous.py
ezneis/data/academy/common.py
ezneis/data/academy/synchronous.py
ezneis/data/school/__init__.py
ezneis/data/school/asynchronous.py
ezneis/data/school/common.py
ezneis/data/school/synchronous.py
ezneis/http/__init__.py
ezneis/http/asynchronous.py
ezneis/http/common.py
ezneis/http/synchronous.py
ezneis/models/__init__.py
ezneis/models/academy_info.py
ezneis/models/classroom.py
ezneis/models/common.py
ezneis/models/department.py
ezneis/models/lecture_room.py
ezneis/models/major.py
ezneis/models/meal.py
ezneis/models/schedule.py
ezneis/models/school_info.py
ezneis/models/time_table.py
ezneis/parsers/__init__.py
ezneis/parsers/academy_info.py
ezneis/parsers/classroom.py
ezneis/parsers/common.py
ezneis/parsers/department.py
ezneis/parsers/lecture_room.py
ezneis/parsers/major.py
ezneis/parsers/meal.py
ezneis/parsers/schedule.py
ezneis/parsers/school_info.py
ezneis/parsers/time_table.py
ezneis/utils/__init__.py
ezneis/utils/caches.py
ezneis/utils/region.py
ezneis/utils/session_manager.py
ezneis/wrappers/__init__.py
ezneis/wrappers/asynchronous.py
ezneis/wrappers/synchronous.py
ezneis-0.1.2.dist-info/LICENSE
ezneis-0.1.2.dist-info/METADATA
ezneis-0.1.2.dist-info/WHEEL
ezneis-0.1.2.dist-info/top_level.txt
ezneis-0.1.2.dist-info/RECORD
