Metadata-Version: 2.1
Name: ezneis
Version: 0.1.2
Summary: ezneis: 나이스 API 파싱 라이브러리
Author-email: DuelitDev <jyoon07dev@gmail.com>
Project-URL: Homepage, https://github.com/DuelitDev/ezneis
Project-URL: Download, https://github.com/DuelitDev/ezneis/tarball/master
Project-URL: Changelog, https://github.com/DuelitDev/ezneis/releases
Project-URL: Documentation, https://github.com/DuelitDev/ezneis/wiki
Project-URL: Issues, https://github.com/DuelitDev/ezneis/issues
Keywords: 나이스,neis,api,neis-api,parse,asyncio
Classifier: Programming Language :: Python :: 3
Classifier: Programming Language :: Python :: 3 :: Only
Classifier: Programming Language :: Python :: 3.10
Classifier: Programming Language :: Python :: 3.11
Classifier: Programming Language :: Python :: 3.12
Classifier: Programming Language :: Python :: 3.13
Classifier: License :: OSI Approved :: MIT License
Requires-Python: >=3.10
License-File: LICENSE
Requires-Dist: requests<3.0.0,>=2.27.0
Requires-Dist: aiohttp<4.0.0,>=3.8.0
